autoanno/__init__.py
autoanno-0.0.1.dev1.dist-info/LICENSE.txt
autoanno-0.0.1.dev1.dist-info/METADATA
autoanno-0.0.1.dev1.dist-info/WHEEL
autoanno-0.0.1.dev1.dist-info/top_level.txt
autoanno-0.0.1.dev1.dist-info/RECORD
