Metadata-Version: 2.1
Name: autoanno
Version: 0.0.1.dev1
Summary: Investigation into using AutoML and Topological Data Analysis for Automated Annotation
Home-page: https://autoanno.readthedocs.io/en/latest/index.html
Author: Matthew Gudorf
Author-email: matthew.gudorf@gmail.com
License: UNKNOWN
Project-URL: documentation, https://autoanno.readthedocs.io/en/latest/index.html
Project-URL: source, https://github.com/mgudorf/autoanno
Project-URL: tutorials, https://github.com/mgudorf/autoanno/tree/main/notebooks
Platform: UNKNOWN
Classifier: Development Status :: 1 - Planning
Classifier: Intended Audience :: Information Technology
Classifier: Topic :: Scientific/Engineering :: Artificial Intelligence
Classifier: Programming Language :: Python :: 3
Classifier: Programming Language :: Python :: 3.7
Classifier: Programming Language :: Python :: 3.8
Classifier: Programming Language :: Python :: 3.9
Classifier: License :: OSI Approved :: GNU General Public License v3 (GPLv3)
Classifier: Operating System :: Microsoft :: Windows :: Windows 10
Requires-Python: >=3.7
Requires-Dist: matplotlib (>=3.1.3)
Requires-Dist: numpy (>=1.18.1)
Requires-Dist: scipy (>=1.4.1)
Requires-Dist: h5py (>=2.10.0)
Requires-Dist: pyqt5 (>=5.15.4)
Requires-Dist: gudhi (>=3.3.0)
Requires-Dist: pot (>=0.7.0)
Requires-Dist: networkx (>=2.5)
Requires-Dist: gensim (>=3.8.3)
Requires-Dist: plotly (>=4.14.3)
Requires-Dist: pytorch (>=1.6.0)
Requires-Dist: ipython (>=7.21.0)
Requires-Dist: ipykernel (>=5.1.4)
Requires-Dist: jupyterlab (>=1.2.6)
Provides-Extra: docs
Requires-Dist: ipython ; extra == 'docs'
Requires-Dist: sphinx (==3.5.2) ; extra == 'docs'
Requires-Dist: sphinxcontrib-log-cabinet (==1.0.1) ; extra == 'docs'
Requires-Dist: sphinx-issues (>=1.2.0) ; extra == 'docs'
Requires-Dist: sphinx-rtd-theme (==0.5.1) ; extra == 'docs'
Requires-Dist: sphinx-gallery (==0.8.2) ; extra == 'docs'
Requires-Dist: numpydoc (>=1.1) ; extra == 'docs'
Requires-Dist: pillow (>=8.0) ; extra == 'docs'
Requires-Dist: nb2plots (>=0.6) ; extra == 'docs'
Requires-Dist: texext (>=0.6.6) ; extra == 'docs'
Requires-Dist: sphinx-tabs (>=2.1.0) ; extra == 'docs'
Provides-Extra: test
Requires-Dist: pytest (>=5.3.5) ; extra == 'test'
